MANIFEST.in
README.md
setup.py
docs/Bibliography.tex
docs/geolevmar_manual.pdf
docs/geolevmar_manual.tex
docs/refs.bib
examples/example_python.py
examples/C/Makefile
examples/C/demo.c
examples/C/demo.o
examples/Fortran/Makefile
examples/Fortran/demo.f90
geodesicLM/Makefile
geodesicLM/README.txt
geodesicLM/__init__.py
geodesicLM/_geodesiclmmodule.c
geodesicLM/accept.f90
geodesicLM/converge.f90
geodesicLM/destsv.f
geodesicLM/dgqt.f
geodesicLM/dpmpar.f
geodesicLM/fdavv.f90
geodesicLM/fdjac.f90
geodesicLM/geodesiclm.f90
geodesicLM/geodesiclm.py
geodesicLM/geodesiclm.pyf
geodesicLM/lambda.f90
geodesicLM/license.txt
geodesicLM/updatejac.f90
geodesicLM.egg-info/PKG-INFO
geodesicLM.egg-info/SOURCES.txt
geodesicLM.egg-info/dependency_links.txt
geodesicLM.egg-info/not-zip-safe
geodesicLM.egg-info/requires.txt
geodesicLM.egg-info/top_level.txt